.DS_Store
xeta/__init__.py
xeta-0.9.4.dist-info/LICENSE
xeta-0.9.4.dist-info/METADATA
xeta-0.9.4.dist-info/WHEEL
xeta-0.9.4.dist-info/top_level.txt
xeta-0.9.4.dist-info/RECORD
