Metadata-Version: 2.1
Name: xeta
Version: 0.9.4
Summary: Official test client
Home-page: https://github.com/xetareality/xeta-python
Author: Xeta
Author-email: contact@xeta.com
License: UNKNOWN
Platform: UNKNOWN
